print_dog/__init__.py
print_dog/__main__.py
print_dog/cli.py
print_dog-0.1.3.dist-info/METADATA
print_dog-0.1.3.dist-info/WHEEL
print_dog-0.1.3.dist-info/entry_points.txt
print_dog-0.1.3.dist-info/top_level.txt
print_dog-0.1.3.dist-info/RECORD
