Metadata-Version: 2.4
Name: print-dog
Version: 0.1.3
Summary: Add your description here
Requires-Python: >=3.12
Requires-Dist: watchdog>=4.0.0
